ngrok/__init__.py
ngrok/client.py
ngrok/datatypes.py
ngrok/error.py
ngrok/http_client.py
ngrok/iterator.py
ngrok/services.py
ngrok/utils.py
ngrok_api-0.19.0.dist-info/licenses/LICENSE
ngrok_api-0.19.0.dist-info/METADATA
ngrok_api-0.19.0.dist-info/WHEEL
ngrok_api-0.19.0.dist-info/top_level.txt
ngrok_api-0.19.0.dist-info/RECORD
