Metadata-Version: 2.4
Name: ngrok-api
Version: 0.19.0
Summary: ngrok HTTP API client library
Home-page: https://github.com/ngrok/ngrok-api-python
Author: Alan Shreve
Author-email: alan@ngrok.com
Classifier: Programming Language :: Python :: 3
Classifier: License :: OSI Approved :: MIT License
Classifier: Operating System :: OS Independent
Requires-Python: >=3.7
License-File: LICENSE
Requires-Dist: requests<3.0,>=2.25.1
Provides-Extra: tox
Requires-Dist: tox==4.32.0; extra == "tox"
Provides-Extra: doc
Requires-Dist: black==21.5b1; extra == "doc"
Requires-Dist: isort==5.11.5; extra == "doc"
Requires-Dist: click==8.0.4; extra == "doc"
Requires-Dist: furo==2022.12.7; extra == "doc"
Requires-Dist: sphinx==6.2.0; extra == "doc"
Requires-Dist: sphinx-autodoc-typehints==1.12.0; extra == "doc"
Requires-Dist: sphinx-readable-theme==1.3.0; extra == "doc"
Requires-Dist: Jinja2==3.0.3; extra == "doc"
Dynamic: author
Dynamic: author-email
Dynamic: classifier
Dynamic: description
Dynamic: description-content-type
Dynamic: home-page
Dynamic: license-file
Dynamic: provides-extra
Dynamic: requires-dist
Dynamic: requires-python
Dynamic: summary
